swtest/__init__.py
swtest/swtest.py
swtest-0.0.9.dist-info/LICENSE
swtest-0.0.9.dist-info/METADATA
swtest-0.0.9.dist-info/WHEEL
swtest-0.0.9.dist-info/top_level.txt
swtest-0.0.9.dist-info/RECORD
