Metadata-Version: 2.1
Name: swtest
Version: 0.0.9
Summary: auto upload test
Home-page: https://pypi.org/
Author: shockwave
Author-email: yao_yingzhe@163.com
License: UNKNOWN
Project-URL: Bug Tracker, https://pypi.org/
Platform: UNKNOWN
Classifier: Programming Language :: Python :: 3
Classifier: License :: OSI Approved :: MIT License
Classifier: Operating System :: OS Independent
Requires-Python: >=3.6
License-File: LICENSE
